tenzir_platform/__init__.py
tenzir_platform/helpers/__init__.py
tenzir_platform/helpers/auth_rule.py
tenzir_platform/helpers/cache.py
tenzir_platform/helpers/client.py
tenzir_platform/helpers/environment.py
tenzir_platform/helpers/exceptions.py
tenzir_platform/helpers/oidc.py
tenzir_platform/subcommand_admin.py
tenzir_platform/subcommand_alert.py
tenzir_platform/subcommand_auth.py
tenzir_platform/subcommand_node.py
tenzir_platform/subcommand_secret.py
tenzir_platform/subcommand_tools.py
tenzir_platform/subcommand_workspace.py
tenzir_platform/tenzir_platform.py
tenzir_platform-1.22.0.dist-info/METADATA
tenzir_platform-1.22.0.dist-info/WHEEL
tenzir_platform-1.22.0.dist-info/entry_points.txt
tenzir_platform-1.22.0.dist-info/RECORD
