Metadata-Version: 2.1
Name: tenzir-platform
Version: 1.22.0
Summary: Tenzir CLI
License: BSD-3-Clause
Author: Tenzir
Author-email: engineering@tenzir.com
Requires-Python: >=3.10,<4.0
Classifier: License :: OSI Approved :: BSD License
Classifier: Programming Language :: Python :: 3
Classifier: Programming Language :: Python :: 3.10
Classifier: Programming Language :: Python :: 3.11
Classifier: Programming Language :: Python :: 3.12
Requires-Dist: base58 (>=2.1.1,<3.0.0)
Requires-Dist: cryptography (>=44.0.1,<45.0.0)
Requires-Dist: docopt (>=0.6.2,<0.7.0)
Requires-Dist: pydantic-settings (>=2.2.1,<3.0.0)
Requires-Dist: pyjwt[crypto] (>=2.8.0,<3.0.0)
Requires-Dist: pytimeparse2 (>=1.7.1,<2.0.0)
Requires-Dist: requests (>=2.31.0,<3.0.0)
Requires-Dist: structlog (>=23.1.0,<24.0.0)
Requires-Dist: types-docopt (>=0.6.11.4,<0.7.0.0)
